dense_ai_det/autoTplt.cp37-win_amd64.pyd
dense_ai_det/autoTplt.cpython-37m-x86_64-linux-gnu.so
dense_ai_det/objectDetector.cp39-win_amd64.pyd
dense_ai_det/transTplt.cp37-win_amd64.pyd
dense_ai_det/transTplt.cp39-win_amd64.pyd
dense_ai_det/transTplt.cpython-37m-x86_64-linux-gnu.so
dense_ai_det-0.1.4.dist-info/METADATA
dense_ai_det-0.1.4.dist-info/WHEEL
dense_ai_det-0.1.4.dist-info/top_level.txt
dense_ai_det-0.1.4.dist-info/RECORD
