Metadata-Version: 2.1
Name: dense_ai_det
Version: 0.1.4
Summary: A common package for dense ai detection
Author: nde
Author-email: hubosoft@hotmail.com
Classifier: Programming Language :: Python :: 3
Classifier: License :: OSI Approved :: MIT License
Classifier: Operating System :: OS Independent
Requires-Python: >=3.6
Requires-Dist: shapely
Requires-Dist: numpy
Requires-Dist: opencv-python
Requires-Dist: Pillow
